edc_form_label/__init__.py
edc_form_label/apps.py
edc_form_label/custom_label_condition.py
edc_form_label/form_label.py
edc_form_label/form_label_modeladmin_mixin.py
edc_form_label/models.py
edc_form_label/urls.py
edc_form_label/tests/__init__.py
edc_form_label/tests/admin.py
edc_form_label/tests/consents.py
edc_form_label/tests/forms.py
edc_form_label/tests/holidays.csv
edc_form_label/tests/models.py
edc_form_label/tests/test_settings.py
edc_form_label/tests/visit_schedule.py
edc_form_label/tests/etc/user-aes-local.key
edc_form_label/tests/etc/user-aes-restricted.key
edc_form_label/tests/etc/user-rsa-local-private.pem
edc_form_label/tests/etc/user-rsa-local-public.pem
edc_form_label/tests/etc/user-rsa-restricted-private.pem
edc_form_label/tests/etc/user-rsa-restricted-public.pem
edc_form_label/tests/etc/user-salt-local.key
edc_form_label/tests/etc/user-salt-restricted.key
edc_form_label/tests/tests/__init__.py
edc_form_label/tests/tests/test_form_label.py
edc_form_label-1.0.2.dist-info/AUTHORS
edc_form_label-1.0.2.dist-info/LICENSE
edc_form_label-1.0.2.dist-info/METADATA
edc_form_label-1.0.2.dist-info/WHEEL
edc_form_label-1.0.2.dist-info/top_level.txt
edc_form_label-1.0.2.dist-info/RECORD
